setup.py
django_with_asserts.egg-info/PKG-INFO
django_with_asserts.egg-info/SOURCES.txt
django_with_asserts.egg-info/dependency_links.txt
django_with_asserts.egg-info/requires.txt
django_with_asserts.egg-info/top_level.txt
with_asserts/__init__.py
with_asserts/case.py
with_asserts/context_manager.py
with_asserts/mixin.py