Metadata-Version: 1.1
Name: django-with-asserts
Version: 0.0.1
Summary: Helpers for testing Django using context managers
Home-page: https://django-with-asserts.readthedocs.org
Author: John Paulett
Author-email: john@paulett.org
License: BSD
Platform: UNKNOWN
Classifier: Intended Audience :: Developers
Classifier: Programming Language :: Python
Classifier: Environment :: Web Environment
Classifier: Framework :: Django
Classifier: License :: OSI Approved :: BSD License
Classifier: Topic :: Software Development :: Testing
